[
  {
    "datetime_index": "201712302200",
    "title": "Kharagpur Winter of Code 2016",
    "short_desc": "Kharagpur Winter of Code is a one-month long open-source contribution fest organised by Kharagpur Open Source Society. As a mentor of ",
    "tags": [
      2,
      3,
      4,
      5,
      7,
      8,
      12,
      13
    ],
    "image_preview": "koss.jpg",
    "images": [
      "1.png",
      "2.png"
    ],
    "hyperlinks": [
      ["Semantic-UI",""]
    ],
    "html_content": "",
    "disqus_identifier": "nzdlaymehbrtcvisojxwfgqpku"
  }
]